cee_syslog_handler/__init__.py
cee_syslog_handler-0.6.0.dist-info/AUTHORS.rst
cee_syslog_handler-0.6.0.dist-info/LICENSE.txt
cee_syslog_handler-0.6.0.dist-info/METADATA
cee_syslog_handler-0.6.0.dist-info/WHEEL
cee_syslog_handler-0.6.0.dist-info/top_level.txt
cee_syslog_handler-0.6.0.dist-info/RECORD
