Metadata-Version: 2.1
Name: cee-syslog-handler
Version: 0.6.0
Summary: Python Syslog Logging Handler with CEE Support
Home-page: https://github.com/blue-yonder/cee_syslog_handler
Author: Blue Yonder GmbH
Author-email: peter.hoffmann@blue-yonder.com
License: new BSD
Platform: UNKNOWN
Classifier: Development Status :: 4 - Beta
Classifier: Environment :: Console
Classifier: Intended Audience :: Developers
Classifier: Intended Audience :: System Administrators
Classifier: License :: OSI Approved :: BSD License
Classifier: Programming Language :: Python :: 3.6
Classifier: Programming Language :: Python :: 3.7
Classifier: Programming Language :: Python :: 3.8
